README.txt
setup.py
broke_students_package/__init__.py
broke_students_package/functions.py
broke_students_package.egg-info/PKG-INFO
broke_students_package.egg-info/SOURCES.txt
broke_students_package.egg-info/dependency_links.txt
broke_students_package.egg-info/requires.txt
broke_students_package.egg-info/top_level.txt