Metadata-Version: 1.0
Name: broke-students-package
Version: 0.1.9
Summary: A Library that shall make you Money....., Or atleast plot it
Home-page: UNKNOWN
Author: The Broke Student Brokers
Author-email: UNKNOWN
License: MIT
Platform: UNKNOWN
